src/__init__.py
src/main.py
src/agents/__init__.py
src/agents/conversation_manager.py
src/agents/test_agent.py
src/agents/test_modifier.py
src/analyzers/__init__.py
src/analyzers/analysis_orchestrator.py
src/analyzers/class_analyzer.py
src/analyzers/code_analyzer.py
src/analyzers/code_parser.py
src/analyzers/complexity_analyzer.py
src/analyzers/coverage_analyzer.py
src/analyzers/coverage_gap_detector.py
src/analyzers/dependency_analyzer.py
src/analyzers/edge_case_detector.py
src/analyzers/function_analyzer.py
src/config/__init__.py
src/config/ai_config.py
src/config/ai_provider_manager.py
src/config/configuration_manager.py
src/factories/__init__.py
src/factories/ai_provider_factory.py
src/factories/analyzer_factory.py
src/factories/generator_factory.py
src/generators/__init__.py
src/generators/edge_test_generator.py
src/generators/integration_test_generator.py
src/generators/test_generator.py
src/generators/unit_test_generator.py
src/integrations/__init__.py
src/integrations/github_actions.py
src/interfaces/__init__.py
src/interfaces/base_interfaces.py
src/utils/explanation_formatter.py
voylla-0.2.3.dist-info/licenses/LICENSE
voylla-0.2.3.dist-info/METADATA
voylla-0.2.3.dist-info/WHEEL
voylla-0.2.3.dist-info/entry_points.txt
voylla-0.2.3.dist-info/top_level.txt
voylla-0.2.3.dist-info/RECORD
