Metadata-Version: 2.4
Name: voylla
Version: 0.2.3
Summary: AI-powered test case generator for Python, Java, and JavaScript with OpenAI, Anthropic, and Google Gemini support
Author: Voylla
License-Expression: MIT
Project-URL: Homepage, https://github.com/AryanSaxenaa/Voylla
Project-URL: Repository, https://github.com/AryanSaxenaa/Voylla
Project-URL: Issues, https://github.com/AryanSaxenaa/Voylla/issues
Classifier: Programming Language :: Python :: 3
Classifier: Operating System :: OS Independent
Classifier: Environment :: Console
Classifier: Topic :: Software Development :: Testing
Requires-Python: >=3.10
License-File: LICENSE
Requires-Dist: click>=8.0.0
Requires-Dist: rich>=13.0.0
Requires-Dist: PyYAML>=6.0
Requires-Dist: python-dotenv>=1.0.0
Requires-Dist: openai>=1.0.0
Requires-Dist: anthropic>=0.7.0
Requires-Dist: google-generativeai>=0.3.0
Requires-Dist: tree-sitter>=0.20.0
Requires-Dist: tree-sitter-python>=0.20.0
Requires-Dist: tree-sitter-javascript>=0.20.0
Requires-Dist: tree-sitter-java>=0.20.0
Dynamic: license-file
